numberclassification/oddeven.py
numberclassification/primes.py
numberclassification-1.0.dist-info/LICENSE
numberclassification-1.0.dist-info/METADATA
numberclassification-1.0.dist-info/WHEEL
numberclassification-1.0.dist-info/top_level.txt
numberclassification-1.0.dist-info/RECORD
