Metadata-Version: 2.1
Name: numberclassification
Version: 1.0
Summary: A tool to classify numbers.
Home-page: UNKNOWN
Author: Marcos Souto
Author-email: marcos.soutofilgueira@gmail.com
License: GNU GPLv3
Keywords: numbers classification
Platform: UNKNOWN
Classifier: Development Status :: 4 - Beta
Classifier: Intended Audience :: Developers
Classifier: Topic :: Utilities
Classifier: License :: OSI Approved :: GNU General Public License v3 (GPLv3)
Classifier: Programming Language :: Python :: 3
Classifier: Operating System :: OS Independent
License-File: LICENSE
